LICENSE
MANIFEST.in
setup.py
protocoin/__init__.py
protocoin/clients.py
protocoin/exceptions.py
protocoin/fields.py
protocoin/keys.py
protocoin/serializers.py
protocoin/util.py
protocoin.egg-info/PKG-INFO
protocoin.egg-info/SOURCES.txt
protocoin.egg-info/dependency_links.txt
protocoin.egg-info/requires.txt
protocoin.egg-info/top_level.txt
protocoin.egg-info/zip-safe