Metadata-Version: 1.1
Name: protocoin
Version: 0.2
Summary: A pure Python bitcoin protocol implementation.
Home-page: https://github.com/perone/protocoin
Author: Christian S. Perone
Author-email: christian.perone@gmail.com
License: BSD License
Keywords: bitcoin,protocol
Platform: Any
Classifier: Development Status :: 4 - Beta
Classifier: Operating System :: OS Independent
Classifier: Programming Language :: Python
Classifier: Topic :: Software Development :: Libraries :: Python Modules
